pgtimer/__init__.py
pgtimer/pgtimer.py
pgtimer-1.0.0.dist-info/licenses/LICENSE
pgtimer-1.0.0.dist-info/METADATA
pgtimer-1.0.0.dist-info/WHEEL
pgtimer-1.0.0.dist-info/top_level.txt
pgtimer-1.0.0.dist-info/RECORD
